{
  "timestamp": "2025-09-15T21:39:14.106788",
  "tokens_scanned": 21,
  "tokens_analyzed": 21,
  "signals_generated": 0,
  "trades_executed": 0,
  "hot_candidates": [],
  "portfolio_value": 10000.0,
  "portfolio_pnl": 0.0,
  "active_positions": 0,
  "performance_metrics": {
    "total_trades": 0,
    "winning_trades": 0,
    "losing_trades": 0,
    "total_pnl": 0.0,
    "max_drawdown": 0.0,
    "sharpe_ratio": 0.0,
    "win_rate": 0.0,
    "profit_factor": 0.0
  },
  "risk_metrics": {
    "portfolio_heat": 0.0,
    "max_portfolio_risk": 0.2,
    "correlation_threshold": 0.7,
    "dynamic_position_sizing": true
  },
  "tokens": [
    {
      "symbol": "WLFI",
      "name": "World Liberty Financial",
      "address": "world-liberty-financial",
      "price": 0.212978,
      "market_cap": 5803871436.0,
      "volume_24h": 846923502.0,
      "price_change_24h": -1.25002,
      "price_change_7d": 0.0,
      "liquidity": 84692350.2,
      "holders": 7493,
      "fresh_holders_1d": 78,
      "fresh_holders_7d": 99,
      "age_minutes": 5,
      "social_score": 0.9,
      "technical_score": 0.7999999999999999,
      "momentum_score": 0.6,
      "risk_score": 0.0,
      "timestamp": "2025-09-15T21:39:00.966815",
      "real_price": 0.212978,
      "real_volume": 846923502.0,
      "real_liquidity": 84692350.2,
      "dex": "coingecko",
      "pair_address": ""
    },
    {
      "symbol": "SOL",
      "name": "Wrapped SOL",
      "address": "So11111111111111111111111111111111111111112",
      "price": 15.399541392710764,
      "market_cap": 597123781.1887522,
      "volume_24h": 5760173.924125133,
      "price_change_24h": 29.440466324130483,
      "price_change_7d": 4.696020001008087,
      "liquidity": 432876.92741255334,
      "holders": 1125,
      "fresh_holders_1d": 16,
      "fresh_holders_7d": 40,
      "age_minutes": 4,
      "social_score": 0.4659286275632619,
      "technical_score": 0.8999999999999999,
      "momentum_score": 0.6,
      "risk_score": 0.0,
      "timestamp": 1757961541,
      "real_price": 15.399541392710764,
      "real_volume": 5760173.924125133,
      "real_liquidity": 432876.92741255334,
      "dex": "Jupiter",
      "pair_address": "So11111111111111111111111111111111111111112"
    },
    {
      "symbol": "USDC",
      "name": "USD Coin",
      "address": "EPjFWdd5AufqSSqeM2qN1xzybapC8G4wEGGkZwyTDt1v",
      "price": 21.57177302590102,
      "market_cap": 423069065.1897678,
      "volume_24h": 4763081.028621281,
      "price_change_24h": -9.547427905530586,
      "price_change_7d": 4.858501505586194,
      "liquidity": 296560.01487620675,
      "holders": 734,
      "fresh_holders_1d": 17,
      "fresh_holders_7d": 40,
      "age_minutes": 1,
      "social_score": 0.8648117973304941,
      "technical_score": 0.7999999999999999,
      "momentum_score": 0.5,
      "risk_score": 0.0,
      "timestamp": 1757961541,
      "real_price": 21.57177302590102,
      "real_volume": 4763081.028621281,
      "real_liquidity": 296560.01487620675,
      "dex": "Jupiter",
      "pair_address": "EPjFWdd5AufqSSqeM2qN1xzybapC8G4wEGGkZwyTDt1v"
    },
    {
      "symbol": "USDT",
      "name": "USDT",
      "address": "Es9vMFrzaCERmJfrF4H2FYD4KCoNkY11McCe8BenwNYB",
      "price": 24.051475826746387,
      "market_cap": 655600579.5053406,
      "volume_24h": 7679781.95650616,
      "price_change_24h": 29.656659167724776,
      "price_change_7d": 49.437950278232904,
      "liquidity": 103950.27773029517,
      "holders": 412,
      "fresh_holders_1d": 10,
      "fresh_holders_7d": 33,
      "age_minutes": 4,
      "social_score": 0.6369477490936399,
      "technical_score": 0.95,
      "momentum_score": 0.5,
      "risk_score": 0.02,
      "timestamp": 1757961541,
      "real_price": 24.051475826746387,
      "real_volume": 7679781.95650616,
      "real_liquidity": 103950.27773029517,
      "dex": "Jupiter",
      "pair_address": "Es9vMFrzaCERmJfrF4H2FYD4KCoNkY11McCe8BenwNYB"
    },
    {
      "symbol": "PYUSD",
      "name": "PayPal USD",
      "address": "2b1kV6DkPAnxd5ixfnxCpjxmKwqjjaYmCZfHsFu24GXo",
      "price": 95.03744271365942,
      "market_cap": 326546635.2486503,
      "volume_24h": 2296945.0700397757,
      "price_change_24h": 47.67358021542911,
      "price_change_7d": 39.23328640227224,
      "liquidity": 454647.5948536477,
      "holders": 5216,
      "fresh_holders_1d": 17,
      "fresh_holders_7d": 34,
      "age_minutes": 5,
      "social_score": 0.7090669592795233,
      "technical_score": 1.0,
      "momentum_score": 0.6,
      "risk_score": 0.0,
      "timestamp": 1757961541,
      "real_price": 95.03744271365942,
      "real_volume": 2296945.0700397757,
      "real_liquidity": 454647.5948536477,
      "dex": "Jupiter",
      "pair_address": "2b1kV6DkPAnxd5ixfnxCpjxmKwqjjaYmCZfHsFu24GXo"
    },
    {
      "symbol": "$WIF",
      "name": "dogwifhat",
      "address": "EKpQGSJtjMFqKZ9KQanSqYXRcF8fBopzLHYxdM65zcjm",
      "price": 86.19191776487664,
      "market_cap": 510491653.7176387,
      "volume_24h": 5635380.795724604,
      "price_change_24h": 20.261601953152372,
      "price_change_7d": 29.10794706457459,
      "liquidity": 349707.78446853155,
      "holders": 3464,
      "fresh_holders_1d": 13,
      "fresh_holders_7d": 22,
      "age_minutes": 1,
      "social_score": 0.30041819580852325,
      "technical_score": 0.8999999999999999,
      "momentum_score": 0.6,
      "risk_score": 0.0,
      "timestamp": 1757961541,
      "real_price": 86.19191776487664,
      "real_volume": 5635380.795724604,
      "real_liquidity": 349707.78446853155,
      "dex": "Jupiter",
      "pair_address": "EKpQGSJtjMFqKZ9KQanSqYXRcF8fBopzLHYxdM65zcjm"
    },
    {
      "symbol": "POPCAT",
      "name": "Popcat",
      "address": "7GCihgDB8fe6KNjn2MYtkzZcRjQy3t9GHdC8uHYmW2hr",
      "price": 64.85613001886921,
      "market_cap": 142409637.50790596,
      "volume_24h": 4841758.23258506,
      "price_change_24h": -5.139894122625506,
      "price_change_7d": 7.270996132294403,
      "liquidity": 109541.19146689418,
      "holders": 1863,
      "fresh_holders_1d": 6,
      "fresh_holders_7d": 23,
      "age_minutes": 4,
      "social_score": 0.7483968787916073,
      "technical_score": 0.7999999999999999,
      "momentum_score": 0.3,
      "risk_score": 0.0,
      "timestamp": 1757961541,
      "real_price": 64.85613001886921,
      "real_volume": 4841758.23258506,
      "real_liquidity": 109541.19146689418,
      "dex": "Jupiter",
      "pair_address": "7GCihgDB8fe6KNjn2MYtkzZcRjQy3t9GHdC8uHYmW2hr"
    },
    {
      "symbol": "JitoSOL",
      "name": "Jito Staked SOL",
      "address": "J1toso1uCk3RLmjorhTtrVwY9HJ7X8V9yYac6Y7kGCPn",
      "price": 44.84849895077131,
      "market_cap": 83323526.14667438,
      "volume_24h": 8590849.76885372,
      "price_change_24h": 49.37734903068912,
      "price_change_7d": 17.64955915764571,
      "liquidity": 309906.32258712524,
      "holders": 730,
      "fresh_holders_1d": 19,
      "fresh_holders_7d": 50,
      "age_minutes": 5,
      "social_score": 0.5352918727079978,
      "technical_score": 1.0,
      "momentum_score": 0.6,
      "risk_score": 0.0,
      "timestamp": 1757961541,
      "real_price": 44.84849895077131,
      "real_volume": 8590849.76885372,
      "real_liquidity": 309906.32258712524,
      "dex": "Jupiter",
      "pair_address": "J1toso1uCk3RLmjorhTtrVwY9HJ7X8V9yYac6Y7kGCPn"
    },
    {
      "symbol": "JUP",
      "name": "Jupiter",
      "address": "JUPyiwrYJFskUPiHa7hkeR8VUtAeFoSYbKedZNsDvCN",
      "price": 87.58203775251341,
      "market_cap": 965289867.9077684,
      "volume_24h": 5922907.705680622,
      "price_change_24h": 36.37457361844042,
      "price_change_7d": 21.029716860145918,
      "liquidity": 376503.05152668944,
      "holders": 7229,
      "fresh_holders_1d": 7,
      "fresh_holders_7d": 34,
      "age_minutes": 4,
      "social_score": 0.4241057331524335,
      "technical_score": 0.95,
      "momentum_score": 0.5,
      "risk_score": 0.0,
      "timestamp": 1757961541,
      "real_price": 87.58203775251341,
      "real_volume": 5922907.705680622,
      "real_liquidity": 376503.05152668944,
      "dex": "Jupiter",
      "pair_address": "JUPyiwrYJFskUPiHa7hkeR8VUtAeFoSYbKedZNsDvCN"
    },
    {
      "symbol": "Bonk",
      "name": "Bonk",
      "address": "DezXAZ8z7PnrnRJjz3wXBoRgixCa6xjnB7YaB1pPB263",
      "price": 75.19801514461756,
      "market_cap": 137838328.5192141,
      "volume_24h": 5785689.743214717,
      "price_change_24h": 45.37359829646698,
      "price_change_7d": 40.756113037546825,
      "liquidity": 357697.8343477058,
      "holders": 2705,
      "fresh_holders_1d": 20,
      "fresh_holders_7d": 45,
      "age_minutes": 4,
      "social_score": 0.4898435422688242,
      "technical_score": 0.95,
      "momentum_score": 0.6,
      "risk_score": 0.0,
      "timestamp": 1757961541,
      "real_price": 75.19801514461756,
      "real_volume": 5785689.743214717,
      "real_liquidity": 357697.8343477058,
      "dex": "Jupiter",
      "pair_address": "DezXAZ8z7PnrnRJjz3wXBoRgixCa6xjnB7YaB1pPB263"
    },
    {
      "symbol": "JLP",
      "name": "Jupiter Perps",
      "address": "27G8MtK7VtTcCHkpASjSDdkWWYfoqT6ggEuKidVJidD4",
      "price": 67.14300181664079,
      "market_cap": 777681279.3338352,
      "volume_24h": 3808555.4628329994,
      "price_change_24h": 26.74804666331555,
      "price_change_7d": -2.289813103994831,
      "liquidity": 298498.2993898868,
      "holders": 4102,
      "fresh_holders_1d": 11,
      "fresh_holders_7d": 39,
      "age_minutes": 1,
      "social_score": 0.6935942380443637,
      "technical_score": 0.95,
      "momentum_score": 0.6,
      "risk_score": 0.0,
      "timestamp": 1757961541,
      "real_price": 67.14300181664079,
      "real_volume": 3808555.4628329994,
      "real_liquidity": 298498.2993898868,
      "dex": "Jupiter",
      "pair_address": "27G8MtK7VtTcCHkpASjSDdkWWYfoqT6ggEuKidVJidD4"
    },
    {
      "symbol": "MUMU",
      "name": "Mumu the Bull",
      "address": "5LafQUrVco6o7KMz42eqVEJ9LW31StPyGjeeu5sKoMtA",
      "price": 28.712864775326327,
      "market_cap": 491740535.07305545,
      "volume_24h": 9513328.457174873,
      "price_change_24h": -2.2854848686284157,
      "price_change_7d": 19.29269773456857,
      "liquidity": 250886.50242308315,
      "holders": 114,
      "fresh_holders_1d": 13,
      "fresh_holders_7d": 15,
      "age_minutes": 3,
      "social_score": 0.8972923780095827,
      "technical_score": 0.75,
      "momentum_score": 0.5,
      "risk_score": 0.05,
      "timestamp": 1757961541,
      "real_price": 28.712864775326327,
      "real_volume": 9513328.457174873,
      "real_liquidity": 250886.50242308315,
      "dex": "Jupiter",
      "pair_address": "5LafQUrVco6o7KMz42eqVEJ9LW31StPyGjeeu5sKoMtA"
    },
    {
      "symbol": "JupSOL",
      "name": "Jupiter Staked SOL",
      "address": "jupSoLaHXQiZZTSfEWMTRRgpnyFm8f6sZdosWBjx93v",
      "price": 58.21454027458461,
      "market_cap": 650122438.9639109,
      "volume_24h": 6579808.919531322,
      "price_change_24h": 11.608970307042135,
      "price_change_7d": 4.314047485319325,
      "liquidity": 179168.50379614613,
      "holders": 2194,
      "fresh_holders_1d": 7,
      "fresh_holders_7d": 38,
      "age_minutes": 2,
      "social_score": 0.709328093323651,
      "technical_score": 0.9,
      "momentum_score": 0.3,
      "risk_score": 0.0,
      "timestamp": 1757961541,
      "real_price": 58.21454027458461,
      "real_volume": 6579808.919531322,
      "real_liquidity": 179168.50379614613,
      "dex": "Jupiter",
      "pair_address": "jupSoLaHXQiZZTSfEWMTRRgpnyFm8f6sZdosWBjx93v"
    },
    {
      "symbol": "mSOL",
      "name": "Marinade staked SOL (mSOL)",
      "address": "mSoLzYCxHdYgdzU16g5QSh3i5K3z3KZK7ytfqcJm7So",
      "price": 19.29506281201393,
      "market_cap": 556752926.7152544,
      "volume_24h": 8336834.987096162,
      "price_change_24h": -15.070881328788342,
      "price_change_7d": 10.40186782202785,
      "liquidity": 479938.48576688813,
      "holders": 4395,
      "fresh_holders_1d": 5,
      "fresh_holders_7d": 40,
      "age_minutes": 4,
      "social_score": 0.8072097339785906,
      "technical_score": 0.7999999999999999,
      "momentum_score": 0.4,
      "risk_score": 0.0,
      "timestamp": 1757961541,
      "real_price": 19.29506281201393,
      "real_volume": 8336834.987096162,
      "real_liquidity": 479938.48576688813,
      "dex": "Jupiter",
      "pair_address": "mSoLzYCxHdYgdzU16g5QSh3i5K3z3KZK7ytfqcJm7So"
    },
    {
      "symbol": "$michi",
      "name": "michi",
      "address": "5mbK36SZ7J19An8jFochhQS4of8g6BwUjbeCSxBSoWdp",
      "price": 9.822418712746305,
      "market_cap": 384460922.8297046,
      "volume_24h": 6986047.925116484,
      "price_change_24h": 24.716491187077622,
      "price_change_7d": 23.396230629785173,
      "liquidity": 315510.10838124424,
      "holders": 9470,
      "fresh_holders_1d": 14,
      "fresh_holders_7d": 24,
      "age_minutes": 4,
      "social_score": 0.8450367382983526,
      "technical_score": 0.95,
      "momentum_score": 0.7,
      "risk_score": 0.0,
      "timestamp": 1757961541,
      "real_price": 9.822418712746305,
      "real_volume": 6986047.925116484,
      "real_liquidity": 315510.10838124424,
      "dex": "Jupiter",
      "pair_address": "5mbK36SZ7J19An8jFochhQS4of8g6BwUjbeCSxBSoWdp"
    },
    {
      "symbol": "BILLY",
      "name": "BILLY",
      "address": "3B5wuUrMEi5yATD7on46hKfej3pfmd7t1RKgrsN3pump",
      "price": 92.9307109269088,
      "market_cap": 778982168.1842343,
      "volume_24h": 1122837.0462109395,
      "price_change_24h": 18.8695576964084,
      "price_change_7d": -8.960400263577634,
      "liquidity": 324707.17061391025,
      "holders": 9737,
      "fresh_holders_1d": 13,
      "fresh_holders_7d": 32,
      "age_minutes": 1,
      "social_score": 0.857831255415215,
      "technical_score": 0.95,
      "momentum_score": 0.5,
      "risk_score": 0.0,
      "timestamp": 1757961541,
      "real_price": 92.9307109269088,
      "real_volume": 1122837.0462109395,
      "real_liquidity": 324707.17061391025,
      "dex": "Jupiter",
      "pair_address": "3B5wuUrMEi5yATD7on46hKfej3pfmd7t1RKgrsN3pump"
    },
    {
      "symbol": "MEW",
      "name": "cat in a dogs world",
      "address": "MEW1gQWJ3nEXg2qgERiKu7FAFj79PHvQVREQUzScPP5",
      "price": 65.59550512956332,
      "market_cap": 36932493.39246358,
      "volume_24h": 8439841.008305883,
      "price_change_24h": 16.242593575338454,
      "price_change_7d": 47.62834633219465,
      "liquidity": 373894.8518963262,
      "holders": 3359,
      "fresh_holders_1d": 9,
      "fresh_holders_7d": 19,
      "age_minutes": 4,
      "social_score": 0.8709167074232955,
      "technical_score": 0.95,
      "momentum_score": 0.4,
      "risk_score": 0.0,
      "timestamp": 1757961541,
      "real_price": 65.59550512956332,
      "real_volume": 8439841.008305883,
      "real_liquidity": 373894.8518963262,
      "dex": "Jupiter",
      "pair_address": "MEW1gQWJ3nEXg2qgERiKu7FAFj79PHvQVREQUzScPP5"
    },
    {
      "symbol": "INF",
      "name": "Infinity",
      "address": "5oVNBeEEQvYi1cX3ir8Dx5n1P7pdxydbGF2X4TxVusJm",
      "price": 83.98054390851594,
      "market_cap": 888330371.1230594,
      "volume_24h": 9517133.130641904,
      "price_change_24h": 22.65591825219432,
      "price_change_7d": -0.5107062046837463,
      "liquidity": 231971.53315514128,
      "holders": 9416,
      "fresh_holders_1d": 8,
      "fresh_holders_7d": 17,
      "age_minutes": 3,
      "social_score": 0.7418745351549756,
      "technical_score": 0.95,
      "momentum_score": 0.5,
      "risk_score": 0.0,
      "timestamp": 1757961541,
      "real_price": 83.98054390851594,
      "real_volume": 9517133.130641904,
      "real_liquidity": 231971.53315514128,
      "dex": "Jupiter",
      "pair_address": "5oVNBeEEQvYi1cX3ir8Dx5n1P7pdxydbGF2X4TxVusJm"
    },
    {
      "symbol": "WBTC",
      "name": "Wrapped BTC (Portal)",
      "address": "3NZ9JMVBmGAqocybic2c7LQCJScmgsAZ6vQqTDzcqmJh",
      "price": 39.687109018816,
      "market_cap": 278861418.7765429,
      "volume_24h": 4924358.193395125,
      "price_change_24h": 41.310985869846796,
      "price_change_7d": 26.461511769660746,
      "liquidity": 156757.3896775503,
      "holders": 3222,
      "fresh_holders_1d": 9,
      "fresh_holders_7d": 47,
      "age_minutes": 3,
      "social_score": 0.6349403519465174,
      "technical_score": 1.0,
      "momentum_score": 0.5,
      "risk_score": 0.0,
      "timestamp": 1757961541,
      "real_price": 39.687109018816,
      "real_volume": 4924358.193395125,
      "real_liquidity": 156757.3896775503,
      "dex": "Jupiter",
      "pair_address": "3NZ9JMVBmGAqocybic2c7LQCJScmgsAZ6vQqTDzcqmJh"
    },
    {
      "symbol": "PONKE",
      "name": "PONKE",
      "address": "5z3EqYQo9HiCEs3R84RCDMu2n7anpDMxRhdK8PSWmrRC",
      "price": 47.87891919134466,
      "market_cap": 712097933.8716959,
      "volume_24h": 5482076.491629362,
      "price_change_24h": 36.61869394821616,
      "price_change_7d": 29.171363435662116,
      "liquidity": 449621.671590693,
      "holders": 2086,
      "fresh_holders_1d": 19,
      "fresh_holders_7d": 23,
      "age_minutes": 5,
      "social_score": 0.8791630537751465,
      "technical_score": 1.0,
      "momentum_score": 0.7,
      "risk_score": 0.0,
      "timestamp": 1757961541,
      "real_price": 47.87891919134466,
      "real_volume": 5482076.491629362,
      "real_liquidity": 449621.671590693,
      "dex": "Jupiter",
      "pair_address": "5z3EqYQo9HiCEs3R84RCDMu2n7anpDMxRhdK8PSWmrRC"
    },
    {
      "symbol": "ETH",
      "name": "Ether (Portal)",
      "address": "7vfCXTUXx5WJV5JADk17DUJ4ksgau7utNKj4b963voxs",
      "price": 47.67951325412169,
      "market_cap": 300594846.70908874,
      "volume_24h": 903633.7510069131,
      "price_change_24h": 1.9735670221715438,
      "price_change_7d": 1.1542745281921718,
      "liquidity": 111615.73008378546,
      "holders": 6592,
      "fresh_holders_1d": 12,
      "fresh_holders_7d": 44,
      "age_minutes": 3,
      "social_score": 0.5573139334214854,
      "technical_score": 0.7999999999999999,
      "momentum_score": 0.4,
      "risk_score": 0.0,
      "timestamp": 1757961541,
      "real_price": 47.67951325412169,
      "real_volume": 903633.7510069131,
      "real_liquidity": 111615.73008378546,
      "dex": "Jupiter",
      "pair_address": "7vfCXTUXx5WJV5JADk17DUJ4ksgau7utNKj4b963voxs"
    }
  ],
  "positions": {},
  "signals": []
}